siegeapi/__init__.py
siegeapi/auth.py
siegeapi/default_stats.py
siegeapi/exceptions.py
siegeapi/linked_accounts.py
siegeapi/maps.py
siegeapi/operators.py
siegeapi/persona.py
siegeapi/player.py
siegeapi/rank_profile.py
siegeapi/ranks.py
siegeapi/summaries.py
siegeapi/trends.py
siegeapi/url_builder.py
siegeapi/utils.py
siegeapi/weapons.py
siegeapi/constants/__init__.py
siegeapi/constants/operators.py
siegeapi/constants/ranks.py
siegeapi/constants/seasons.py
siegeapi/constants/weapons.py
siegeapi-6.3.5.dist-info/licenses/LICENSE
siegeapi-6.3.5.dist-info/METADATA
siegeapi-6.3.5.dist-info/WHEEL
siegeapi-6.3.5.dist-info/top_level.txt
siegeapi-6.3.5.dist-info/RECORD
